dillnet/__init__.py
dillnet/dillnet.py
dillnet-1.1.0.dist-info/licenses/LICENSE
dillnet-1.1.0.dist-info/METADATA
dillnet-1.1.0.dist-info/WHEEL
dillnet-1.1.0.dist-info/top_level.txt
dillnet-1.1.0.dist-info/RECORD
