Metadata-Version: 2.4
Name: dillnet
Version: 1.1.0
Summary: Dill custom model.
Home-page: https://github.com/dillfrescott/dillnet
Author: Cross Nastasi
Author-email: cross@dill.moe
Classifier: Programming Language :: Python :: 3
Classifier: License :: OSI Approved :: MIT License
Classifier: Operating System :: OS Independent
Requires-Python: >=3.6
License-File: LICENSE
Requires-Dist: torch
Dynamic: license-file
